waffle_hub/__init__.py
waffle_hub/dataset/__init__.py
waffle_hub/dataset/cli.py
waffle_hub/dataset/dataset.py
waffle_hub/dataset/adapter/__init__.py
waffle_hub/dataset/adapter/autocare_dlt.py
waffle_hub/dataset/adapter/coco.py
waffle_hub/dataset/adapter/label_studio.py
waffle_hub/dataset/adapter/transformers.py
waffle_hub/dataset/adapter/yolo.py
waffle_hub/experimental/__init__.py
waffle_hub/experimental/serve.py
waffle_hub/experimental/auto_label/__init__.py
waffle_hub/experimental/auto_label/auto_label.py
waffle_hub/experimental/auto_label/extract_frames.py
waffle_hub/hub/__init__.py
waffle_hub/hub/cli.py
waffle_hub/hub/hub.py
waffle_hub/hub/adapter/__init__.py
waffle_hub/hub/adapter/autocare_dlt/__init__.py
waffle_hub/hub/adapter/autocare_dlt/autocare_dlt_hub.py
waffle_hub/hub/adapter/autocare_dlt/config.py
waffle_hub/hub/adapter/autocare_dlt/configs/__init__.py
waffle_hub/hub/adapter/autocare_dlt/configs/data_cfg.py
waffle_hub/hub/adapter/autocare_dlt/configs/model_cfg.py
waffle_hub/hub/adapter/transformers/__init__.py
waffle_hub/hub/adapter/transformers/config.py
waffle_hub/hub/adapter/transformers/train_input_helper.py
waffle_hub/hub/adapter/transformers/transformers_hub.py
waffle_hub/hub/adapter/ultralytics/__init__.py
waffle_hub/hub/adapter/ultralytics/config.py
waffle_hub/hub/adapter/ultralytics/ultralytics_hub.py
waffle_hub/hub/model/__init__.py
waffle_hub/hub/model/wrapper.py
waffle_hub/schema/__init__.py
waffle_hub/schema/base_schema.py
waffle_hub/schema/configs.py
waffle_hub/schema/data.py
waffle_hub/schema/evaluate.py
waffle_hub/schema/result.py
waffle_hub/schema/running_status.py
waffle_hub/schema/fields/__init__.py
waffle_hub/schema/fields/annotation.py
waffle_hub/schema/fields/base_field.py
waffle_hub/schema/fields/category.py
waffle_hub/schema/fields/image.py
waffle_hub/temp_utils/__init__.py
waffle_hub/temp_utils/image/__init__.py
waffle_hub/temp_utils/image/io.py
waffle_hub/temp_utils/video/__init__.py
waffle_hub/temp_utils/video/io.py
waffle_hub-0.3.1.dist-info/LICENSE
waffle_hub-0.3.1.dist-info/METADATA
waffle_hub-0.3.1.dist-info/WHEEL
waffle_hub-0.3.1.dist-info/entry_points.txt
waffle_hub-0.3.1.dist-info/top_level.txt
waffle_hub-0.3.1.dist-info/RECORD
