Metadata-Version: 2.1
Name: waffle_hub
Version: 0.3.1
Summary: Waffle hub
Home-page: https://github.com/snuailab/waffle_hub
Author: SNUAILAB
Author-email: huijae.lee@snuailab.ai
License: GPL-3.0
Project-URL: Bug Reports, https://github.com/snuailab/waffle_hub/issues
Project-URL: Source, https://github.com/snuailab/waffle_hub
Keywords: machine-learning,deep-learning,vision,ML,DL,AI,YOLO,Ultralytics,SNUAILAB
Classifier: Development Status :: 3 - Alpha
Classifier: Intended Audience :: Developers
Classifier: Intended Audience :: Science/Research
Classifier: License :: OSI Approved :: GNU General Public License v3 (GPLv3)
Classifier: Programming Language :: Python :: 3.9
Classifier: Programming Language :: Python :: 3.10
Classifier: Topic :: Software Development
Classifier: Topic :: Scientific/Engineering
Classifier: Topic :: Scientific/Engineering :: Artificial Intelligence
Classifier: Topic :: Scientific/Engineering :: Image Recognition
Classifier: Operating System :: POSIX :: Linux
Requires-Python: >=3.9
License-File: LICENSE
Requires-Dist: tqdm
Requires-Dist: tabulate ==0.9.0
Requires-Dist: pydantic >=2.4.1
Requires-Dist: rich ==13.5.2
Requires-Dist: onnxruntime ==1.15.1
Requires-Dist: tbparse ==0.0.7
Requires-Dist: waffle-utils >=1.1.0
Requires-Dist: ultralytics ==8.0.227
Requires-Dist: datasets ==2.12.0
Requires-Dist: transformers ==4.28.1
Requires-Dist: albumentations ==1.3.0
Requires-Dist: evaluate ==0.4.0
Requires-Dist: timm ==0.6.13
Requires-Dist: autocare-dlt ==0.2.6
Requires-Dist: numpy <=1.23.5
Requires-Dist: torchmetrics ==1.1.0
Requires-Dist: pycocotools >=2.0.2
Requires-Dist: py-cpuinfo >=8.0.0
Requires-Dist: shapely >=2.0.0
Requires-Dist: fire ==0.5.0
Requires-Dist: Pillow ==9.5.0
Requires-Dist: fsspec <2023.10.0
Requires-Dist: sentry-sdk
